cnprep/__init__.py
cnprep/extractor.py
cnprep/zh2num.py
cnprep-0.1.11.dist-info/DESCRIPTION.rst
cnprep-0.1.11.dist-info/METADATA
cnprep-0.1.11.dist-info/RECORD
cnprep-0.1.11.dist-info/WHEEL
cnprep-0.1.11.dist-info/metadata.json
cnprep-0.1.11.dist-info/top_level.txt
