Metadata-Version: 2.0
Name: cnprep
Version: 0.1.11
Summary: A lib for Chinese text preprocessing
Home-page: https://github.com/momingcoder/cnprep
Author: Keming Yang
Author-email: a398445075@gmail.com
License: MIT
Download-URL: https://github.com/momingcoder/cnprep/tarball/0.1.11
Keywords: Chinese,text,preprocess
Platform: UNKNOWN
Classifier: Topic :: Text Processing
Classifier: Programming Language :: Python :: 3.5
Requires-Dist: xpinyin
